ezstools/__init__.py
ezstools/console_utils.py
ezstools/errorshelp.py
ezstools/funcs.py
ezstools/homoglyphs_subs.json
ezstools/html_slice.py
ezstools/iterator.py
ezstools/json_tools.py
ezstools/module_tools.py
ezstools/pygm.py
ezstools/random_generator.py
ezstools/simple_kv.py
ezstools/string_tools.py
ezstools/traits.py
ezstools-3.6.4.dist-info/METADATA
ezstools-3.6.4.dist-info/WHEEL
ezstools-3.6.4.dist-info/licenses/LICENSE
ezstools-3.6.4.dist-info/RECORD
