Metadata-Version: 2.1
Name: ezstools
Version: 3.6.4
Summary: Multi-purpose utility package
Author-email: Hendrick <hendrickrodriguez.py@gmail.com>
License-File: LICENSE
Classifier: License :: OSI Approved :: MIT License
Classifier: Operating System :: OS Independent
Classifier: Programming Language :: Python :: 3
Requires-Python: >=3.11
Requires-Dist: pick
